pun_nlp/__init__.py
pun_nlp/processor.py
pun_nlp-0.0.9.dist-info/licenses/LICENSE
tests/__init__.py
tests/test_processor.py
pun_nlp-0.0.9.dist-info/METADATA
pun_nlp-0.0.9.dist-info/WHEEL
pun_nlp-0.0.9.dist-info/top_level.txt
pun_nlp-0.0.9.dist-info/RECORD
